fluidattacks_success_indicators/__init__.py
fluidattacks_success_indicators/_core.py
fluidattacks_success_indicators/_logger.py
fluidattacks_success_indicators/py.typed
fluidattacks_success_indicators/_cli/__init__.py
fluidattacks_success_indicators/_cli/_sub_cmds.py
fluidattacks_success_indicators/_db_client/__init__.py
fluidattacks_success_indicators/_db_client/_client_1.py
fluidattacks_success_indicators/_db_client/_connection.py
fluidattacks_success_indicators/_db_client/_core.py
fluidattacks_success_indicators/_db_client/_creds.py
fluidattacks_success_indicators/_factory/__init__.py
fluidattacks_success_indicators/_factory/_connection.py
fluidattacks_success_indicators-3.1.0.dist-info/entry_points.txt
fluidattacks_success_indicators-3.1.0.dist-info/WHEEL
fluidattacks_success_indicators-3.1.0.dist-info/METADATA
fluidattacks_success_indicators-3.1.0.dist-info/RECORD
