Metadata-Version: 2.4
Name: fluidattacks_success_indicators
Version: 3.1.0
Summary: job last success reporter
Author-email: Product Team <development@fluidattacks.com>
Requires-Python: >=3.11
Classifier: License :: OSI Approved :: MIT License
Requires-Dist: click >=8.3.0, <9.0.0
Requires-Dist: fa-purity >=2.5.2, <3.0.0
Requires-Dist: fluidattacks-connection-manager >=2.0.0, <3.0.0
Requires-Dist: fluidattacks-etl-utils >=2.0.0, <3.0.0
Requires-Dist: fluidattacks-utils-logger >=3.0.0, <4.0.0
